cai_common/__init__.py
cai_common/defaults.py
cai_common/data/__init__.py
cai_common/data/corpus_loader.py
cai_common/data/open_pecha_loaders.py
cai_common/data/parallel_tmx_loader.py
cai_common/data/symbol_cleaning.json
cai_common/data/tei_loader.py
cai_common/data/utils.py
cai_common/datasets/__init__.py
cai_common/datasets/token_tag_dataset.py
cai_common/dict/__init__.py
cai_common/dict/dict.py
cai_common/dict/numbers.py
cai_common/models/__init__.py
cai_common/models/utils.py
cai_common/utils/__init__.py
cai_common/utils/file_utils.py
cai_common/utils/hydra_training_args.py
cai_common/utils/parallel_shuffle.py
cai_common/utils/tensorboard_callback.py
compassionai_common-0.2.2.dist-info/LICENSE
compassionai_common-0.2.2.dist-info/METADATA
compassionai_common-0.2.2.dist-info/WHEEL
compassionai_common-0.2.2.dist-info/top_level.txt
compassionai_common-0.2.2.dist-info/RECORD
