Metadata-Version: 2.1
Name: compassionai-common
Version: 0.2.2
Summary: Common components for CompassionAI projects
Home-page: https://github.com/compassionai/common
Author: CompassionAI
Author-email: contact@compassion-ai.org
Project-URL: Bug Tracker, https://github.com/compassionai/issues
Classifier: Intended Audience :: Science/Research
Classifier: License :: OSI Approved :: GNU General Public License v3 (GPLv3)
Classifier: Programming Language :: Python :: 3.6
Classifier: Topic :: Scientific/Engineering :: Artificial Intelligence
Requires-Python: >=3.6
License-File: LICENSE
Requires-Dist: torch (>=1.12.1)
Requires-Dist: transformers (==4.23.1)
